contractvm-0.6.9.16.dist-info/DESCRIPTION.rst
contractvm-0.6.9.16.dist-info/METADATA
contractvm-0.6.9.16.dist-info/RECORD
contractvm-0.6.9.16.dist-info/WHEEL
contractvm-0.6.9.16.dist-info/entry_points.txt
contractvm-0.6.9.16.dist-info/metadata.json
contractvm-0.6.9.16.dist-info/top_level.txt
contractvmd/__init__.py
contractvmd/api.py
contractvmd/chainstarter.py
contractvmd/config.py
contractvmd/contractvmd.py
contractvmd/dapp.py
contractvmd/dappman.py
contractvmd/database.py
contractvmd/dht.py
contractvmd/pluginmanager.py
contractvmd/proto.py
contractvmd/backend/__init__.py
contractvmd/backend/backend.py
contractvmd/backend/chainsoapi.py
contractvmd/backend/daemonrpc.py
contractvmd/backend/node.py
contractvmd/chain/__init__.py
contractvmd/chain/blockwatch.py
contractvmd/chain/chain.py
contractvmd/chain/message.py
