Metadata-Version: 2.0
Name: contractvm
Version: 0.6.9.16
Summary: A general-purpose framework for decentralized applications
Home-page: UNKNOWN
Author: Davide Gessa
Author-email: gessadavide@gmail.com
License: UNKNOWN
Platform: UNKNOWN
Requires-Dist: base58
Requires-Dist: bitpeer.py
Requires-Dist: colorlog
Requires-Dist: json-rpc
Requires-Dist: kad.py
Requires-Dist: lxml
Requires-Dist: pycoin (==0.62)
Requires-Dist: requests
Requires-Dist: werkzeug
